tests/__init__.py
tests/test_crypto.py
xchainpy_crypto/__init__.py
xchainpy_crypto/crypto.py
xchainpy_crypto/utils.py
xchainpy_crypto/models/CipherParams.py
xchainpy_crypto/models/CryptoStruct.py
xchainpy_crypto/models/KdfParams.py
xchainpy_crypto/models/Keystore.py
xchainpy_crypto/models/__init__.py
xchainpy_crypto-0.1.11.dist-info/LICENSE
xchainpy_crypto-0.1.11.dist-info/METADATA
xchainpy_crypto-0.1.11.dist-info/WHEEL
xchainpy_crypto-0.1.11.dist-info/top_level.txt
xchainpy_crypto-0.1.11.dist-info/RECORD
