Metadata-Version: 2.1
Name: xchainpy-crypto
Version: 0.1.11
Summary: XCHAIN-CRYPTO encrypts a master phrase to a keystore
Home-page: https://github.com/xchainjs/xchainpy-lib/tree/main/xchainpy/xchainpy_crypto
Author: THORChain
License: MIT
Keywords: THORChain,XChainpy,XChainpy_crypto
Platform: UNKNOWN
Classifier: Intended Audience :: Developers
Classifier: Topic :: Software Development :: Libraries :: Python Modules
Classifier: License :: OSI Approved :: MIT License
Classifier: Programming Language :: Python :: 3
Classifier: Programming Language :: Python :: 3.6
Classifier: Programming Language :: Python :: 3.7
Classifier: Programming Language :: Python
License-File: LICENSE
Requires-Dist: mnemonic (>=0.18)
Requires-Dist: bip-utils (==1.11.1)
Requires-Dist: pycryptodome (==3.11.0)
